pyoformats/__init__.py
pyoformats/read.py
pyoformats/version.py
pyoformats/res/log4j.properties
pyoformats-1.1.3.dist-info/METADATA
pyoformats-1.1.3.dist-info/RECORD
pyoformats-1.1.3.dist-info/WHEEL
pyoformats-1.1.3.dist-info/top_level.txt
