Metadata-Version: 2.1
Name: pyoformats
Version: 1.1.3
Summary: PyoFormats: Simple wrapper for python-bioformats
Home-page: https://git.ist.ac.at/csommer/pyoformats
Author: Christoph Sommer, Wiebke Jahr
Author-email: christoph.sommer23@gmail.com, wiebke.jahr@ist.ac.at
License: BSD
Platform: UNKNOWN
Classifier: Development Status :: 4 - Beta
Classifier: Programming Language :: Python :: 3
Classifier: License :: OSI Approved :: BSD License
Requires-Dist: numpy
Requires-Dist: javabridge
Requires-Dist: python-bioformats
